<?xml version="1.0" encoding="utf-8"?>
<annotation>
	<folder>2</folder>
	<filename>115.jpg</filename>
	<path>/home/wayne/workspace/food_data/115.jpg</path>
	<source>
		<database>UECfood256</database>
	</source>
	<size>
		<width>200</width>
		<height>137</height>
		<depth>3</depth>
	</size>
	<segmented>0</segmented>
	<object>
		<name>eels on rice</name>
		<pose>Unspecified</pose>
		<truncated>0</truncated>
		<difficult>0</difficult>
		<bndbox>
			<xmin>3</xmin>
			<ymin>7</ymin>
			<xmax>196</xmax>
			<ymax>134</ymax>
		</bndbox>
	</object>
</annotation>
